{
    "Equitable Distribution": {
        "definition": "the distribution of marital assets by a court in a divorce action in accordance with statutory guidelines that are designed to produce a fair but not necessarily equal division of the property",
        "sub_definitions": {
            "1": {
                "1": "the distribution of marital assets by a court in a divorce action in accordance with statutory guidelines that are designed to produce a fair but not necessarily equal division of the property"
            }
        },
        "references": {}
    }
}