{
    "Feres Doctrine": {
        "definition": "a doctrine in tort law",
        "origin": "[from Feres v. United States , 340 U.S. 135 (1950), the case which established the doctrine]",
        "sub_definitions": {
            "1": {
                "1": "a doctrine in tort law: a member of the military is barred from recovering damages from the government under the Federal Tort Claims Act for injuries sustained in the course of activity incident to his or her military service called also"
            }
        },
        "references": {}
    }
}