{
    "File Wrapper": {
        "definition": "a written record in a patent office of the application and negotiations for a patent preceding the issuance of the patent see also file wrapper estoppel at estoppel",
        "sub_definitions": {
            "1": {
                "1": "a written record in a patent office of the application and negotiations for a patent preceding the issuance of the patent see also"
            }
        },
        "references": {
            "estoppel": "https://dictionary.findlaw.com/definition/estoppel.html"
        }
    }
}