{
    "Justify": {
        "definition": "to prove or show to be just",
        "origin": "[does not a denial of bail]",
        "sub_definitions": {
            "1": {
                "definition": "to show a legally sufficient reason for an act"
            },
            "2": {
                "definition": "to swear an oath as to the ownership of sufficient property [they shall in an amount no less than $200 \"\"]to qualify as a surety by swearing such an oath [the defendants sought to as bail \", 253 A.2d 341 (1969)\"]",
                "State v. Blaisdell": "253 A.2d 341 (1969)"
            }
        },
        "references": {}
    }
}