{
    "Saving Clause": {
        "definition": "a clause in a statute exempting something from the statute's operation or providing that the rest of it will stand if part is held invalid ;also",
        "sub_definitions": {
            "1": {
                "1": "a clause in a statute exempting something from the statute's operation or providing that the rest of it will stand if part is held invalid"
            },
            "2": {
                "1": "a contractual clause providing that if part of the contract is invalidated the rest shall remain in effect called also"
            }
        },
        "references": {}
    }
}