{
    "Semble": {
        "definition": "it seems [ that the two statutes are consistent] used chiefly to indicate obiter dictum usually parenthetically following a citation or to introduce a tentative thought",
        "origin": "[ that the two statutes are consistent]",
        "sub_definitions": {
            "1": {
                "1": "it seems [ that the two statutes are consistent] used chiefly to indicate obiter dictum usually parenthetically following a citation or to introduce a tentative thought"
            }
        },
        "references": {}
    }
}