{
    "Silent Witness Theory": {
        "definition": "a theory or rule in the law of evidence",
        "sub_definitions": {
            "1": {
                "1": "a theory or rule in the law of evidence: photographic evidence (as photographs or videotapes) produced by a process whose reliability is established may be admitted as substantive evidence of what it depicts without the need for an eyewitness to verify the accuracy of its depiction"
            }
        },
        "references": {}
    }
}