{
    "Undertaking": {
        "definition": "a promise or pledge esp. required by law 2",
        "sub_definitions": {
            "1": {
                "definition": "a promise or pledge esp. required by law"
            },
            "2": {
                "definition": "something (as cash or a written promise) deposited or given as security esp. in a court",
                "note": " Undertakings are often required of one party during property actions (as for attachment) in order to compensate the other party should the court's action (as in attaching the property) be found unjustified later."
            }
        },
        "references": {}
    }
}