{
    "Vandalism": {
        "definition": "the willful or malicious destruction or defacement of property [insurance covering property damage from and malicious mischief]",
        "origin": "[insurance covering property damage from and malicious mischief]",
        "sub_definitions": {
            "1": {
                "1": "the willful or malicious destruction or defacement of property [insurance covering property damage from and malicious mischief]"
            }
        },
        "references": {}
    }
}